snok/__init__.py
snok/cli.py
snok/const.py
snok/py.typed
snok/utils.py
snok/services/__init__.py
snok/services/generator.py
snok/services/new.py
snok/templates/__app/_.env.dev
snok/templates/__app/_.env.test
snok/templates/__app/__init__.py
snok/templates/__app/_modal.py
snok/templates/__app/_types.py
snok/templates/__app/app.py
snok/templates/__app/config.py
snok/templates/__app/const.py
snok/templates/__app/database.py
snok/templates/__app/exceptions.py
snok/templates/__app/logger.py
snok/templates/__app/router.py
snok/templates/__app/health/__init__.py
snok/templates/__app/health/router.py
snok/templates/__app/health/schemas.py
snok/templates/__app/kit/__init__.py
snok/templates/__app/kit/db.py
snok/templates/__app/kit/routers.py
snok/templates/__app/modal_testing/__init__.py
snok/templates/__app/modal_testing/router.py
snok/templates/__app/models/__init__.py
snok/templates/__app_migrations/README
snok/templates/__app_migrations/alembic.ini
snok/templates/__app_migrations/env.py
snok/templates/__app_migrations/script.py.mako
snok/templates/__app_migrations/versions/_.keep
snok/templates/__app_models/model.py
snok/templates/__app_router/router.py
snok/templates/__app_scaffold/router.py
snok/templates/__app_scaffold/schemas.py
snok/templates/__app_scaffold/service.py
snok/templates/__app_scaffold_tests/test_router.py
snok/templates/__app_scaffold_views/_form.html
snok/templates/__app_scaffold_views/base.html
snok/templates/__app_scaffold_views/edit.html
snok/templates/__app_scaffold_views/index.html
snok/templates/__app_scaffold_views/new.html
snok/templates/__app_scaffold_views/show.html
snok/templates/__app_static/tailwind.config.js
snok/templates/__app_static/css/input.css
snok/templates/__app_static/images/favicon.png
snok/templates/__app_static/images/logo.png
snok/templates/__app_static/js/htmx/1.9.2/htmx-json-enc.min.js
snok/templates/__app_static/js/htmx/1.9.2/htmx.min.js
snok/templates/__app_tests/__init__.py
snok/templates/__app_tests/conftest.py
snok-0.0.17.dist-info/LICENSE
snok-0.0.17.dist-info/METADATA
snok-0.0.17.dist-info/WHEEL
snok-0.0.17.dist-info/entry_points.txt
snok-0.0.17.dist-info/top_level.txt
snok-0.0.17.dist-info/RECORD
