Metadata-Version: 2.1
Name: snok
Version: 0.0.17
Summary: 🚀 A simple, modern, full-stack toolkit for Python 🐍
Author-email: Anthony Corletti <anthcor+snok@gmail.com>
License: MIT
Project-URL: Home, https://github.com/anthonycorletti/snok
Project-URL: Documentation, https://snok.corletti.xyz
Requires-Python: >=3.11
License-File: LICENSE
Requires-Dist: httpx >=0.24.1
Requires-Dist: invoke >=1.6.0
Requires-Dist: jinja2 >=3.1.2
Requires-Dist: packaging >=21.0
Requires-Dist: pydantic >=1.8.2
Requires-Dist: rich >=13.4.2
Requires-Dist: setuptools >=67.8.0
Requires-Dist: toml >=0.10.2
Requires-Dist: typer >=0.7.0
Requires-Dist: wheel >=0.36
Provides-Extra: dev
Requires-Dist: asgi-lifespan >=2.1.0 ; extra == 'dev'
Requires-Dist: black >=21.10 ; extra == 'dev'
Requires-Dist: coverage >=7.2.7 ; extra == 'dev'
Requires-Dist: greenlet >=2.0.2 ; extra == 'dev'
Requires-Dist: mdx-include >=1.4.2 ; extra == 'dev'
Requires-Dist: mkdocs-material >=9.1.5 ; extra == 'dev'
Requires-Dist: mkdocs >=1.4.2 ; extra == 'dev'
Requires-Dist: mypy >=0.910 ; extra == 'dev'
Requires-Dist: pre-commit >=2.17.0 ; extra == 'dev'
Requires-Dist: pytest-asyncio >=0.21.1 ; extra == 'dev'
Requires-Dist: pytest-cov >=3.0.0 ; extra == 'dev'
Requires-Dist: pytest-xdist >=3.3.1 ; extra == 'dev'
Requires-Dist: pytest >=6.2.5 ; extra == 'dev'
Requires-Dist: ruff >=0.0.98 ; extra == 'dev'
Requires-Dist: types-toml >=0.1.0 ; extra == 'dev'
Requires-Dist: watchfiles >=0.19.0 ; extra == 'dev'
